{"metadata": {"resultset": {"offset": 35001, "count": 38860, "limit": 25}}, "results": [{"mindate": "1995-06-01", "maxdate": "2020-03-15", "name": "Lindon, UT 84042", "datacoverage": 0.95, "id": "ZIP:84042"}, {"mindate": "1904-06-09", "maxdate": "2020-03-15", "name": "Lehi, UT 84043", "datacoverage": 1, "id": "ZIP:84043"}, {"mindate": "1903-07-19", "maxdate": "2020-03-15", "name": "Magna, UT 84044", "datacoverage": 1, "id": "ZIP:84044"}, {"mindate": "1995-06-01", "maxdate": "2020-03-15", "name": "Saratoga Springs, UT 84045", "datacoverage": 0.95, "id": "ZIP:84045"}, {"mindate": "1925-10-01", "maxdate": "2020-03-15", "name": "Manila, UT 84046", "datacoverage": 1, "id": "ZIP:84046"}, {"mindate": "1911-10-01", "maxdate": "2020-03-15", "name": "Midvale, UT 84047", "datacoverage": 1, "id": "ZIP:84047"}, {"mindate": "1914-01-01", "maxdate": "2020-03-15", "name": "Midway, UT 84049", "datacoverage": 1, "id": "ZIP:84049"}, {"mindate": "1903-01-01", "maxdate": "2020-03-15", "name": "Morgan, UT 84050", "datacoverage": 1, "id": "ZIP:84050"}, {"mindate": "1910-06-01", "maxdate": "2020-03-15", "name": "Mountain Home, UT 84051", "datacoverage": 1, "id": "ZIP:84051"}, {"mindate": "1915-08-27", "maxdate": "2020-03-15", "name": "Myton, UT 84052", "datacoverage": 1, "id": "ZIP:84052"}, {"mindate": "1915-09-01", "maxdate": "2020-03-15", "name": "Neola, UT 84053", "datacoverage": 1, "id": "ZIP:84053"}, {"mindate": "1995-06-01", "maxdate": "2020-03-15", "name": "North Salt Lake, UT 84054", "datacoverage": 0.95, "id": "ZIP:84054"}, {"mindate": "1995-06-01", "maxdate": "2020-03-15", "name": "Oakley, UT 84055", "datacoverage": 0.95, "id": "ZIP:84055"}, {"mindate": "1914-01-19", "maxdate": "2020-03-16", "name": "Hill AFB, UT 84056", "datacoverage": 1, "id": "ZIP:84056"}, {"mindate": "1963-09-01", "maxdate": "2020-03-15", "name": "Orem, UT 84057", "datacoverage": 1, "id": "ZIP:84057"}, {"mindate": "1953-01-01", "maxdate": "2020-03-15", "name": "Orem, UT 84058", "datacoverage": 1, "id": "ZIP:84058"}, {"mindate": "1896-03-01", "maxdate": "2020-03-15", "name": "Park City, UT 84060", "datacoverage": 1, "id": "ZIP:84060"}, {"mindate": "1974-07-01", "maxdate": "2020-03-15", "name": "Peoa, UT 84061", "datacoverage": 1, "id": "ZIP:84061"}, {"mindate": "1946-09-01", "maxdate": "2020-03-15", "name": "Pleasant Grove, UT 84062", "datacoverage": 1, "id": "ZIP:84062"}, {"mindate": "1996-06-05", "maxdate": "2020-03-15", "name": "Randlett, UT 84063", "datacoverage": 0.95, "id": "ZIP:84063"}, {"mindate": "1893-03-01", "maxdate": "2020-03-15", "name": "Randolph, UT 84064", "datacoverage": 1, "id": "ZIP:84064"}, {"mindate": "1965-07-01", "maxdate": "2020-03-15", "name": "Riverton, UT 84065", "datacoverage": 1, "id": "ZIP:84065"}, {"mindate": "1935-06-04", "maxdate": "2020-03-15", "name": "Roosevelt, UT 84066", "datacoverage": 1, "id": "ZIP:84066"}, {"mindate": "1948-01-01", "maxdate": "2020-03-16", "name": "Roy, UT 84067", "datacoverage": 1, "id": "ZIP:84067"}, {"mindate": "1925-01-01", "maxdate": "2020-03-15", "name": "Rush Valley, UT 84069", "datacoverage": 1, "id": "ZIP:84069"}]}