{"metadata": {"resultset": {"offset": 18001, "count": 38860, "limit": 25}}, "results": [{"mindate": "1931-01-01", "maxdate": "2020-03-15", "name": "Fort Walton Beach, FL 32547", "datacoverage": 1, "id": "ZIP:32547"}, {"mindate": "1994-08-15", "maxdate": "2020-03-15", "name": "Fort Walton Beach, FL 32548", "datacoverage": 0.9997, "id": "ZIP:32548"}, {"mindate": "1994-08-15", "maxdate": "2020-03-15", "name": "Miramar Beach, FL 32550", "datacoverage": 0.95, "id": "ZIP:32550"}, {"mindate": "1994-08-15", "maxdate": "2020-03-15", "name": "Gulf Breeze, FL 32561", "datacoverage": 0.9819, "id": "ZIP:32561"}, {"mindate": "1994-08-15", "maxdate": "2020-03-15", "name": "Gulf Breeze, FL 32563", "datacoverage": 1, "id": "ZIP:32563"}, {"mindate": "1994-08-15", "maxdate": "2020-03-15", "name": "Holt, FL 32564", "datacoverage": 1, "id": "ZIP:32564"}, {"mindate": "1948-08-01", "maxdate": "2020-03-15", "name": "Jay, FL 32565", "datacoverage": 1, "id": "ZIP:32565"}, {"mindate": "1967-02-01", "maxdate": "2020-03-15", "name": "Navarre, FL 32566", "datacoverage": 1, "id": "ZIP:32566"}, {"mindate": "1994-08-15", "maxdate": "2020-03-15", "name": "Laurel Hill, FL 32567", "datacoverage": 0.95, "id": "ZIP:32567"}, {"mindate": "1994-08-15", "maxdate": "2020-03-15", "name": "Mc David, FL 32568", "datacoverage": 0.95, "id": "ZIP:32568"}, {"mindate": "1955-07-01", "maxdate": "2020-03-16", "name": "Mary Esther, FL 32569", "datacoverage": 1, "id": "ZIP:32569"}, {"mindate": "1961-01-01", "maxdate": "2020-03-16", "name": "Milton, FL 32570", "datacoverage": 1, "id": "ZIP:32570"}, {"mindate": "1994-08-15", "maxdate": "2020-03-15", "name": "Milton, FL 32571", "datacoverage": 1, "id": "ZIP:32571"}, {"mindate": "1902-03-01", "maxdate": "2020-03-15", "name": "Molino, FL 32577", "datacoverage": 1, "id": "ZIP:32577"}, {"mindate": "1949-09-01", "maxdate": "2020-03-15", "name": "Niceville, FL 32578", "datacoverage": 1, "id": "ZIP:32578"}, {"mindate": "1994-08-15", "maxdate": "2020-03-15", "name": "Shalimar, FL 32579", "datacoverage": 1, "id": "ZIP:32579"}, {"mindate": "1927-02-01", "maxdate": "2020-03-15", "name": "Valparaiso, FL 32580", "datacoverage": 1, "id": "ZIP:32580"}, {"mindate": "1994-08-15", "maxdate": "2020-03-15", "name": "Milton, FL 32583", "datacoverage": 1, "id": "ZIP:32583"}, {"mindate": "1995-06-16", "maxdate": "2020-03-15", "name": "Gainesville, FL 32601", "datacoverage": 1, "id": "ZIP:32601"}, {"mindate": "1995-06-16", "maxdate": "2020-03-15", "name": "Gainesville, FL 32603", "datacoverage": 0.9751, "id": "ZIP:32603"}, {"mindate": "1995-06-16", "maxdate": "2020-03-15", "name": "Gainesville, FL 32605", "datacoverage": 1, "id": "ZIP:32605"}, {"mindate": "1995-06-16", "maxdate": "2020-03-15", "name": "Gainesville, FL 32606", "datacoverage": 1, "id": "ZIP:32606"}, {"mindate": "1995-06-16", "maxdate": "2020-03-15", "name": "Gainesville, FL 32607", "datacoverage": 1, "id": "ZIP:32607"}, {"mindate": "1953-10-01", "maxdate": "2020-03-15", "name": "Gainesville, FL 32608", "datacoverage": 1, "id": "ZIP:32608"}, {"mindate": "1943-11-01", "maxdate": "2020-03-16", "name": "Gainesville, FL 32609", "datacoverage": 1, "id": "ZIP:32609"}]}