{"metadata": {"resultset": {"offset": 2001, "count": 38860, "limit": 25}}, "results": [{"mindate": "1892-12-01", "maxdate": "2020-03-16", "name": "South Central Arizona Climate Division", "datacoverage": 1, "id": "CLIM:0406"}, {"mindate": "1867-08-01", "maxdate": "2020-03-16", "name": "Southeast Arizona Climate Division", "datacoverage": 1, "id": "CLIM:0407"}, {"mindate": "1891-11-01", "maxdate": "2020-03-16", "name": "Northwest Arkansas Climate Division", "datacoverage": 1, "id": "CLIM:0501"}, {"mindate": "1892-01-01", "maxdate": "2020-03-16", "name": "North Central Arkansas Climate Division", "datacoverage": 1, "id": "CLIM:0502"}, {"mindate": "1871-07-01", "maxdate": "2020-03-16", "name": "Northeast Arkansas Climate Division", "datacoverage": 1, "id": "CLIM:0503"}, {"mindate": "1886-06-01", "maxdate": "2020-03-16", "name": "West Central Arkansas Climate Division", "datacoverage": 1, "id": "CLIM:0504"}, {"mindate": "1874-06-01", "maxdate": "2020-03-16", "name": "Central Arkansas Climate Division", "datacoverage": 1, "id": "CLIM:0505"}, {"mindate": "1883-04-01", "maxdate": "2020-03-16", "name": "East Central Arkansas Climate Division", "datacoverage": 1, "id": "CLIM:0506"}, {"mindate": "1872-02-01", "maxdate": "2020-03-16", "name": "Southwest Arkansas Climate Division", "datacoverage": 1, "id": "CLIM:0507"}, {"mindate": "1886-01-01", "maxdate": "2020-03-16", "name": "South Central Arkansas Climate Division", "datacoverage": 1, "id": "CLIM:0508"}, {"mindate": "1884-05-01", "maxdate": "2020-03-16", "name": "Southeast Arkansas Climate Division", "datacoverage": 1, "id": "CLIM:0509"}, {"mindate": "1873-01-01", "maxdate": "2020-03-16", "name": "North Coast Drainage California Climate Division", "datacoverage": 1, "id": "CLIM:0601"}, {"mindate": "1856-01-01", "maxdate": "2020-03-16", "name": "Sacramento Drng. California Climate Division", "datacoverage": 1, "id": "CLIM:0602"}, {"mindate": "1867-06-01", "maxdate": "2020-03-16", "name": "Northeast Inter. Basins California Climate Division", "datacoverage": 1, "id": "CLIM:0603"}, {"mindate": "1893-01-01", "maxdate": "2020-03-16", "name": "Central Coast Drng. California Climate Division", "datacoverage": 1, "id": "CLIM:0604"}, {"mindate": "1879-01-01", "maxdate": "2020-03-16", "name": "San Joaquin Drng. California Climate Division", "datacoverage": 1, "id": "CLIM:0605"}, {"mindate": "1850-10-01", "maxdate": "2020-03-16", "name": "South Coast Drng. California Climate Division", "datacoverage": 1, "id": "CLIM:0606"}, {"mindate": "1888-07-01", "maxdate": "2020-03-16", "name": "Southeast Desert Basin California Climate Division", "datacoverage": 1, "id": "CLIM:0607"}, {"mindate": "1893-01-01", "maxdate": "2020-03-16", "name": "Arkansas Drainage Basin Colorado Climate Division", "datacoverage": 1, "id": "CLIM:0801"}, {"mindate": "1885-02-01", "maxdate": "2020-03-16", "name": "Colorado Drainage Basin Colorado Climate Division", "datacoverage": 1, "id": "CLIM:0802"}, {"mindate": "1893-01-01", "maxdate": "2020-03-16", "name": "Kansas Drainage Basin Colorado Climate Division", "datacoverage": 1, "id": "CLIM:0803"}, {"mindate": "1893-01-01", "maxdate": "2020-03-16", "name": "Platte Drainage Basin Colorado Climate Division", "datacoverage": 1, "id": "CLIM:0804"}, {"mindate": "1852-10-01", "maxdate": "2020-03-16", "name": "Rio Grande Drainage Basin Colorado Climate Division", "datacoverage": 1, "id": "CLIM:0805"}, {"mindate": "1884-11-01", "maxdate": "2020-03-15", "name": "Northwest Connecticut Climate Division", "datacoverage": 1, "id": "CLIM:0901"}, {"mindate": "1884-11-01", "maxdate": "2020-03-16", "name": "Central Connecticut Climate Division", "datacoverage": 1, "id": "CLIM:0902"}]}